TopDownCrawl/TopDownCrawl.py
TopDownCrawl/__init__.py
TopDownCrawl/__main__.py
TopDownCrawl-1.0.1.dist-info/LICENSE
TopDownCrawl-1.0.1.dist-info/METADATA
TopDownCrawl-1.0.1.dist-info/WHEEL
TopDownCrawl-1.0.1.dist-info/entry_points.txt
TopDownCrawl-1.0.1.dist-info/top_level.txt
TopDownCrawl-1.0.1.dist-info/RECORD
