Metadata-Version: 2.1
Name: TopDownCrawl
Version: 1.0.1
Summary: TopDownCrawl is a tool for aligning quantitative binding data for k-mers from experiments such as SELEX-seq and SMiLE-seq
Home-page: https://github.com/bhcooper/TopDownCrawl
Author: Brendon Cooper
License: UNKNOWN
Platform: UNKNOWN
Classifier: Programming Language :: Python :: 3
Classifier: License :: OSI Approved :: MIT License
Classifier: Operating System :: OS Independent
License-File: LICENSE
Requires-Dist: pandas
Requires-Dist: matplotlib
Requires-Dist: logomaker
Requires-Dist: fonts
Requires-Dist: font-roboto
Requires-Dist: xlrd
Requires-Dist: openpyxl
